bugs/__init__.py
bugs/quixbugs/__init__.py
bugs/quixbugs/python_pytest/__init__.py
bugs/quixbugs/python_pytest/bitcount_test.py
bugs/quixbugs/python_pytest/bucketsort_test.py
bugs/quixbugs/python_pytest/find_first_in_sorted_test.py
bugs/quixbugs/python_pytest/find_in_sorted_test.py
bugs/quixbugs/python_pytest/flatten_test.py
bugs/quixbugs/python_pytest/gcd_test.py
bugs/quixbugs/python_pytest/get_factors_test.py
bugs/quixbugs/python_pytest/hanoi_test.py
bugs/quixbugs/python_pytest/is_valid_parenthesization_test.py
bugs/quixbugs/python_pytest/kheapsort_test.py
bugs/quixbugs/python_pytest/knapsack_test.py
bugs/quixbugs/python_pytest/kth_test.py
bugs/quixbugs/python_pytest/lcs_length_test.py
bugs/quixbugs/python_pytest/levenshtein_test.py
bugs/quixbugs/python_pytest/lis_test.py
bugs/quixbugs/python_pytest/longest_common_subsequence_test.py
bugs/quixbugs/python_pytest/max_sublist_sum_test.py
bugs/quixbugs/python_pytest/mergesort_test.py
bugs/quixbugs/python_pytest/next_palindrome_test.py
bugs/quixbugs/python_pytest/next_permutation_test.py
bugs/quixbugs/python_pytest/pascal_test.py
bugs/quixbugs/python_pytest/possible_change_test.py
bugs/quixbugs/python_pytest/powerset_test.py
bugs/quixbugs/python_pytest/quicksort_test.py
bugs/quixbugs/python_pytest/rpn_eval_test.py
bugs/quixbugs/python_pytest/shunting_yard_test.py
bugs/quixbugs/python_pytest/sieve_test.py
bugs/quixbugs/python_pytest/sqrt_test.py
bugs/quixbugs/python_pytest/subsequences_test.py
bugs/quixbugs/python_pytest/to_base_test.py
bugs/quixbugs/python_pytest/wrap_test.py
bugs/quixbugs/python_pytest/python_programs/__init__.py
bugs/quixbugs/python_pytest/python_programs/bitcount.py
bugs/quixbugs/python_pytest/python_programs/breadth_first_search.py
bugs/quixbugs/python_pytest/python_programs/breadth_first_search_test.py
bugs/quixbugs/python_pytest/python_programs/bucketsort.py
bugs/quixbugs/python_pytest/python_programs/depth_first_search.py
bugs/quixbugs/python_pytest/python_programs/depth_first_search_test.py
pyimprove-0.0.3.dist-info/LICENSE
pyimprove-0.0.3.dist-info/METADATA
pyimprove-0.0.3.dist-info/WHEEL
pyimprove-0.0.3.dist-info/top_level.txt
pyimprove-0.0.3.dist-info/RECORD
