Metadata-Version: 2.1
Name: pyimprove
Version: 0.0.3
Summary: Automated Program Repair of Python Source-Code Using Genetic Improvement
Home-page: https://gitlab.com/WilliamWCYoung/pyimprove
Author: William Young
Author-email: william.w.c.young@hotmail.com
License: UNKNOWN
Platform: UNKNOWN
Classifier: Programming Language :: Python :: 3.7
Classifier: License :: OSI Approved :: MIT License
Classifier: Operating System :: OS Independent
